zeal/__init__.py
zeal/apps.py
zeal/constants.py
zeal/errors.py
zeal/listeners.py
zeal/middleware.py
zeal/patch.py
zeal/signals.py
zeal/util.py
django_zeal-2.0.3.dist-info/LICENSE
django_zeal-2.0.3.dist-info/METADATA
django_zeal-2.0.3.dist-info/WHEEL
django_zeal-2.0.3.dist-info/top_level.txt
django_zeal-2.0.3.dist-info/RECORD
