Metadata-Version: 2.2
Name: django-zeal
Version: 2.0.3
Summary: Detect N+1s in your Django app
License: Copyright 2016 Joshua Carp
Requires-Python: >=3.9
License-File: LICENSE
